<?xml version="1.0" encoding="UTF-8" standalone="no"?>
<instance:xArch xmlns:instance="http://www.ics.uci.edu/pub/arch/xArch/instance.xsd" xmlns:changes="http://www.ics.uci.edu/pub/arch/xArch/changes.xsd" xmlns:hints3="http://www.ics.uci.edu/pub/arch/xArch/hints3.xsd" xmlns:implementation="http://www.ics.uci.edu/pub/arch/xArch/implementation.xsd" xmlns:implementationext="http://www.ics.uci.edu/pub/arch/xArch/implementationext.xsd" xmlns:javaimplementation="http://www.ics.uci.edu/pub/arch/xArch/javaimplementation.xsd" xmlns:lookupimplementation="http://www.ics.uci.edu/pub/arch/xArch/lookupimplementation.xsd" xmlns:types="http://www.ics.uci.edu/pub/arch/xArch/types.xsd" xmlns:xlink="http://www.w3.org/1999/xlink" xmlns:xsi="http://www.w3.org/2001/XMLSchema-instance" xsi:schemaLocation="http://www.ics.uci.edu/pub/arch/xArch/lookupimplementation.xsd http://www.isr.uci.edu/projects/xarchuci/ext/lookupimplementation.xsd http://www.ics.uci.edu/pub/arch/xArch/variants.xsd http://www.isr.uci.edu/projects/xarchuci/ext/variants.xsd http://www.ics.uci.edu/pub/arch/xArch/javaimplementation.xsd http://www.isr.uci.edu/projects/xarchuci/ext/javaimplementation.xsd http://www.ics.uci.edu/pub/arch/xArch/implementation.xsd http://www.isr.uci.edu/projects/xarchuci/ext/implementation.xsd http://www.ics.uci.edu/pub/arch/xArch/implementationext.xsd http://www.ics.uci.edu/~zhengy/schema/Implementationext.xsd http://www.ics.uci.edu/pub/arch/xArch/changes.xsd http://www.ics.uci.edu/~zhengy/schema/changes.xsd http://www.ics.uci.edu/pub/arch/xArch/hints3.xsd http://www.isr.uci.edu/projects/xarchuci/ext/hints3.xsd http://www.ics.uci.edu/pub/arch/xArch/instance.xsd http://www.isr.uci.edu/projects/xarchuci/core/instance.xsd http://www.ics.uci.edu/pub/arch/xArch/statecharts.xsd http://www.ics.uci.edu/~zhengy/schema/statecharts.xsd http://www.ics.uci.edu/pub/arch/xArch/interactions.xsd http://www.ics.uci.edu/~zhengy/schema/interactions.xsd http://www.ics.uci.edu/pub/arch/xArch/types.xsd http://www.isr.uci.edu/projects/xarchuci/ext/types.xsd http://www.ics.uci.edu/pub/arch/xArch/changesets.xsd http://www.isr.uci.edu/projects/xarchuci/ext/changesets.xsd">
    <types:archStructure types:id="archStructureff97002a-09d445c8-c928a06b-f7a90002" xsi:type="types:ArchStructure">
        <types:description xsi:type="instance:Description">tomcat_arch</types:description>
        <types:component types:id="componentff97002a-09d8520f-6e554146-f7a900a3" xsi:type="implementationext:ComponentImpl">
            <types:description xsi:type="instance:Description">bootstrap</types:description>
            <implementationext:implementation xsi:type="javaimplementation:JavaImplementation">
                <javaimplementation:mainClass xsi:type="javaimplementation:JavaClassFile">
                    <javaimplementation:javaClassName xsi:type="javaimplementation:JavaClassName">bootstrap.bootstrapArch</javaimplementation:javaClassName>
                </javaimplementation:mainClass>
                <javaimplementation:auxClass xsi:type="javaimplementation:JavaClassFile">
                    <javaimplementation:javaClassName xsi:type="javaimplementation:JavaClassName">bootstrap.bootstrapImp</javaimplementation:javaClassName>
                </javaimplementation:auxClass>
            </implementationext:implementation>
        </types:component>
        <types:component types:id="componentfffffffc-40c8adcf-462f118c-86330028" xsi:type="implementationext:ComponentImpl">
            <types:description xsi:type="instance:Description">server</types:description>
            <types:interface types:id="interfacefffffffc-40fb019b-ac120043-863300e8" xsi:type="types:Interface">
                <types:description xsi:type="instance:Description">[New Interface]</types:description>
                <types:direction xsi:type="instance:Direction">out</types:direction>
                <types:type xlink:href="#interfaceTypefffffffc-40f4e5d0-7d5b65f9-86330098" xlink:type="simple" xsi:type="instance:XMLLink"/>
            </types:interface>
            <types:interface types:id="interfacefffffffc-40fb9d63-6c2936a1-8633012f" xsi:type="types:Interface">
                <types:description xsi:type="instance:Description">[New Interface]</types:description>
                <types:direction xsi:type="instance:Direction">in</types:direction>
                <types:type xlink:href="#interfaceTypefffffffc-40f550f9-9c233e65-8633009a" xlink:type="simple" xsi:type="instance:XMLLink"/>
            </types:interface>
            <implementationext:implementation xsi:type="javaimplementation:JavaImplementation">
                <javaimplementation:mainClass xsi:type="javaimplementation:JavaClassFile">
                    <javaimplementation:javaClassName xsi:type="javaimplementation:JavaClassName">tomcat.server.serverArch</javaimplementation:javaClassName>
                </javaimplementation:mainClass>
                <javaimplementation:auxClass xsi:type="javaimplementation:JavaClassFile">
                    <javaimplementation:javaClassName xsi:type="javaimplementation:JavaClassName">tomcat.server.serverImp</javaimplementation:javaClassName>
                </javaimplementation:auxClass>
            </implementationext:implementation>
        </types:component>
        <types:component types:id="componentfffffffc-40f4820d-7bd2f699-86330068" xsi:type="implementationext:ComponentImpl">
            <types:description xsi:type="instance:Description">service</types:description>
            <types:interface types:id="interfacefffffffc-40fb3293-16fa1f03-8633010a" xsi:type="types:Interface">
                <types:description xsi:type="instance:Description">[New Interface]</types:description>
                <types:direction xsi:type="instance:Direction">in</types:direction>
                <types:type xlink:href="#interfaceTypefffffffc-40f4e5d0-7d5b65f9-86330098" xlink:type="simple" xsi:type="instance:XMLLink"/>
            </types:interface>
            <types:interface types:id="interfacefffffffc-40fbeb12-4f3d7217-86330153" xsi:type="types:Interface">
                <types:description xsi:type="instance:Description">[New Interface]</types:description>
                <types:direction xsi:type="instance:Direction">out</types:direction>
                <types:type xlink:href="#interfaceTypefffffffc-40f550f9-9c233e65-8633009a" xlink:type="simple" xsi:type="instance:XMLLink"/>
            </types:interface>
            <types:interface types:id="interfacefffffffc-417dcf35-9b587455-cebe02be" xsi:type="types:Interface">
                <types:description xsi:type="instance:Description">[New Interface]</types:description>
                <types:direction xsi:type="instance:Direction">out</types:direction>
                <types:type xlink:href="#interfaceTypefffffffc-4179dcd1-22c497de-cebe02a2" xlink:type="simple" xsi:type="instance:XMLLink"/>
            </types:interface>
            <types:interface types:id="interfacefffffffc-417e990b-1a8d697a-cebe0328" xsi:type="types:Interface">
                <types:description xsi:type="instance:Description">[New Interface]</types:description>
                <types:direction xsi:type="instance:Direction">in</types:direction>
                <types:type xlink:href="#interfaceTypefffffffc-417a12cc-c94b7ed8-cebe02a3" xlink:type="simple" xsi:type="instance:XMLLink"/>
            </types:interface>
            <implementationext:implementation xsi:type="javaimplementation:JavaImplementation">
                <javaimplementation:mainClass xsi:type="javaimplementation:JavaClassFile">
                    <javaimplementation:javaClassName xsi:type="javaimplementation:JavaClassName">tomcat.service.serviceArch</javaimplementation:javaClassName>
                </javaimplementation:mainClass>
                <javaimplementation:auxClass xsi:type="javaimplementation:JavaClassFile">
                    <javaimplementation:javaClassName xsi:type="javaimplementation:JavaClassName">tomcat.service.serviceImp</javaimplementation:javaClassName>
                </javaimplementation:auxClass>
            </implementationext:implementation>
            
            
            
        </types:component>
        <types:component types:id="componentfffffffc-41792677-b03beb03-cebe0262" xsi:type="implementationext:ComponentImpl">
            <types:description xsi:type="instance:Description">engine</types:description>
            <types:interface types:id="interfacefffffffc-417e19bf-4aeb042f-cebe02e1" xsi:type="types:Interface">
                <types:description xsi:type="instance:Description">[New Interface]</types:description>
                <types:direction xsi:type="instance:Direction">in</types:direction>
                <types:type xlink:href="#interfaceTypefffffffc-4179dcd1-22c497de-cebe02a2" xlink:type="simple" xsi:type="instance:XMLLink"/>
            </types:interface>
            <types:interface types:id="interfacefffffffc-417e6457-97880f1b-cebe0305" xsi:type="types:Interface">
                <types:description xsi:type="instance:Description">[New Interface]</types:description>
                <types:direction xsi:type="instance:Direction">out</types:direction>
                <types:type xlink:href="#interfaceTypefffffffc-417a12cc-c94b7ed8-cebe02a3" xlink:type="simple" xsi:type="instance:XMLLink"/>
            </types:interface>
            <implementationext:implementation xsi:type="javaimplementation:JavaImplementation">
                <javaimplementation:mainClass xsi:type="javaimplementation:JavaClassFile">
                    <javaimplementation:javaClassName xsi:type="javaimplementation:JavaClassName">tomcat.engine.engineArch</javaimplementation:javaClassName>
                </javaimplementation:mainClass>
                <javaimplementation:auxClass xsi:type="javaimplementation:JavaClassFile">
                    <javaimplementation:javaClassName xsi:type="javaimplementation:JavaClassName">tomcat.engine.engineImp</javaimplementation:javaClassName>
                </javaimplementation:auxClass>
            </implementationext:implementation>
            
            
            
        </types:component>
        <types:link types:id="linkfffffffc-40fd2e61-71bb67c8-cebe0030" xsi:type="types:Link">
            <types:description xsi:type="instance:Description">[New Link]</types:description>
            <types:point xsi:type="instance:Point">
                <instance:anchorOnInterface xlink:href="#interfacefffffffc-40fb019b-ac120043-863300e8" xlink:type="simple" xsi:type="instance:XMLLink"/>
            </types:point>
            <types:point xsi:type="instance:Point">
                <instance:anchorOnInterface xlink:href="#interfacefffffffc-40fb3293-16fa1f03-8633010a" xlink:type="simple" xsi:type="instance:XMLLink"/>
            </types:point>
        </types:link>
        <types:link types:id="linkfffffffc-40fd7571-7c301f45-cebe005f" xsi:type="types:Link">
            <types:description xsi:type="instance:Description">[New Link]</types:description>
            <types:point xsi:type="instance:Point">
                <instance:anchorOnInterface xlink:href="#interfacefffffffc-40fb9d63-6c2936a1-8633012f" xlink:type="simple" xsi:type="instance:XMLLink"/>
            </types:point>
            <types:point xsi:type="instance:Point">
                <instance:anchorOnInterface xlink:href="#interfacefffffffc-40fbeb12-4f3d7217-86330153" xlink:type="simple" xsi:type="instance:XMLLink"/>
            </types:point>
        </types:link>
        <types:link types:id="linkfffffffc-4180cad5-e82c2104-ea3a0056" xsi:type="types:Link">
            <types:description xsi:type="instance:Description">[New Link]</types:description>
            <types:point xsi:type="instance:Point">
                <instance:anchorOnInterface xlink:href="#interfacefffffffc-417dcf35-9b587455-cebe02be" xlink:type="simple" xsi:type="instance:XMLLink"/>
            </types:point>
            <types:point xsi:type="instance:Point">
                <instance:anchorOnInterface xlink:href="#interfacefffffffc-417e19bf-4aeb042f-cebe02e1" xlink:type="simple" xsi:type="instance:XMLLink"/>
            </types:point>
        </types:link>
        <types:link types:id="linkfffffffc-4180faaf-3b96e8be-ea3a0066" xsi:type="types:Link">
            <types:description xsi:type="instance:Description">[New Link]</types:description>
            <types:point xsi:type="instance:Point">
                <instance:anchorOnInterface xlink:href="#interfacefffffffc-417e990b-1a8d697a-cebe0328" xlink:type="simple" xsi:type="instance:XMLLink"/>
            </types:point>
            <types:point xsi:type="instance:Point">
                <instance:anchorOnInterface xlink:href="#interfacefffffffc-417e6457-97880f1b-cebe0305" xlink:type="simple" xsi:type="instance:XMLLink"/>
            </types:point>
        </types:link>
        
        
        
        
        
        
        
        
        
        
        
        
        
    </types:archStructure>
    <hints3:renderingHints3 xsi:type="hints3:RenderingHints3">
        <hints3:hintedElement hints3:maintainer="edu.uci.isr.archstudio4.comp.archipelago" hints3:version="4.0.0" xsi:type="hints3:HintBundle"/>
        <hints3:hintedElement hints3:maintainer="edu.uci.isr.archstudio4.comp.archipelago" hints3:version="4.1.0" xsi:type="hints3:HintBundle">
            <hints3:hintedElement xsi:type="hints3:HintedElement">
                <hints3:target xlink:href="#archStructureff97002a-09d445c8-c928a06b-f7a90002" xlink:type="simple" xsi:type="instance:XMLLink"/>
                <hints3:hintedElement xsi:type="hints3:HintedElement">
                    <hints3:target xlink:href="#componentff97002a-09d49a42-09ad963d-f7a90006" xlink:type="simple" xsi:type="instance:XMLLink"/>
                    <hints3:property hints3:name="glass/boundingBox" xsi:type="hints3:Property">
                        <hints3:value hints3:data="10172,10113,100,100" hints3:type="org.eclipse.swt.graphics.Rectangle" xsi:type="hints3:PropertyValue"/>
                    </hints3:property>
                </hints3:hintedElement>
                <hints3:hintedElement xsi:type="hints3:HintedElement">
                    <hints3:target xlink:href="#componentff97002a-09d69ee0-a10a8f1b-f7a90048" xlink:type="simple" xsi:type="instance:XMLLink"/>
                    <hints3:property hints3:name="glass/boundingBox" xsi:type="hints3:Property">
                        <hints3:value hints3:data="10176,10162,100,100" hints3:type="org.eclipse.swt.graphics.Rectangle" xsi:type="hints3:PropertyValue"/>
                    </hints3:property>
                </hints3:hintedElement>
                <hints3:hintedElement xsi:type="hints3:HintedElement">
                    <hints3:target xlink:href="#componentff97002a-09d8520f-6e554146-f7a900a3" xlink:type="simple" xsi:type="instance:XMLLink"/>
                    <hints3:property hints3:name="glass/boundingBox" xsi:type="hints3:Property">
                        <hints3:value hints3:data="10375,9750,100,100" hints3:type="org.eclipse.swt.graphics.Rectangle" xsi:type="hints3:PropertyValue"/>
                    </hints3:property>
                    <hints3:property hints3:name="background/color" xsi:type="hints3:Property">
                        <hints3:value hints3:data="197,203,255" hints3:type="org.eclipse.swt.graphics.RGB" xsi:type="hints3:PropertyValue"/>
                    </hints3:property>
                    
                    
                </hints3:hintedElement>
                <hints3:hintedElement xsi:type="hints3:HintedElement">
                    <hints3:target xlink:href="#componentfffffffc-40c8adcf-462f118c-86330028" xlink:type="simple" xsi:type="instance:XMLLink"/>
                    <hints3:property hints3:name="glass/boundingBox" xsi:type="hints3:Property">
                        <hints3:value hints3:data="9950,10000,900,150" hints3:type="org.eclipse.swt.graphics.Rectangle" xsi:type="hints3:PropertyValue"/>
                    </hints3:property>
                    <hints3:property hints3:name="background/color" xsi:type="hints3:Property">
                        <hints3:value hints3:data="197,203,255" hints3:type="org.eclipse.swt.graphics.RGB" xsi:type="hints3:PropertyValue"/>
                    </hints3:property>
                </hints3:hintedElement>
                <hints3:hintedElement xsi:type="hints3:HintedElement">
                    <hints3:target xlink:href="#componentfffffffc-40f4820d-7bd2f699-86330068" xlink:type="simple" xsi:type="instance:XMLLink"/>
                    <hints3:property hints3:name="glass/boundingBox" xsi:type="hints3:Property">
                        <hints3:value hints3:data="10075,10400,675,125" hints3:type="org.eclipse.swt.graphics.Rectangle" xsi:type="hints3:PropertyValue"/>
                    </hints3:property>
                    <hints3:property hints3:name="background/color" xsi:type="hints3:Property">
                        <hints3:value hints3:data="232,234,255" hints3:type="org.eclipse.swt.graphics.RGB" xsi:type="hints3:PropertyValue"/>
                    </hints3:property>
                </hints3:hintedElement>
                <hints3:hintedElement xsi:type="hints3:HintedElement">
                    <hints3:target xlink:href="#interfacefffffffc-40fb019b-ac120043-863300e8" xlink:type="simple" xsi:type="instance:XMLLink"/>
                    <hints3:property hints3:name="glass/anchorPoint" xsi:type="hints3:Property">
                        <hints3:value hints3:data="10167,10150" hints3:type="org.eclipse.swt.graphics.Point" xsi:type="hints3:PropertyValue"/>
                    </hints3:property>
                    <hints3:property hints3:name="glass/anchorPoint-StuckInfo" xsi:type="hints3:Property">
                        <hints3:value hints3:data="{EDGE,{0.24148148,1.0}}" hints3:type="{[Ljava.lang.Object;,2,enum:edu.uci.isr.bna4.logics.coordinating.MaintainStickyPointLogic$StickyMode,{[F,2,java.lang.Float,java.lang.Float}}" xsi:type="hints3:PropertyValue"/>
                    </hints3:property>
                    <hints3:property hints3:name="background/color" xsi:type="hints3:Property">
                        <hints3:value hints3:data="255,255,255" hints3:type="org.eclipse.swt.graphics.RGB" xsi:type="hints3:PropertyValue"/>
                    </hints3:property>
                </hints3:hintedElement>
                <hints3:hintedElement xsi:type="hints3:HintedElement">
                    <hints3:target xlink:href="#interfacefffffffc-40fb3293-16fa1f03-8633010a" xlink:type="simple" xsi:type="instance:XMLLink"/>
                    <hints3:property hints3:name="glass/anchorPoint" xsi:type="hints3:Property">
                        <hints3:value hints3:data="10244,10400" hints3:type="org.eclipse.swt.graphics.Point" xsi:type="hints3:PropertyValue"/>
                    </hints3:property>
                    <hints3:property hints3:name="glass/anchorPoint-StuckInfo" xsi:type="hints3:Property">
                        <hints3:value hints3:data="{EDGE,{0.2504348,0.0}}" hints3:type="{[Ljava.lang.Object;,2,enum:edu.uci.isr.bna4.logics.coordinating.MaintainStickyPointLogic$StickyMode,{[F,2,java.lang.Float,java.lang.Float}}" xsi:type="hints3:PropertyValue"/>
                    </hints3:property>
                    <hints3:property hints3:name="background/color" xsi:type="hints3:Property">
                        <hints3:value hints3:data="255,255,255" hints3:type="org.eclipse.swt.graphics.RGB" xsi:type="hints3:PropertyValue"/>
                    </hints3:property>
                </hints3:hintedElement>
                <hints3:hintedElement xsi:type="hints3:HintedElement">
                    <hints3:target xlink:href="#interfacefffffffc-40fb9d63-6c2936a1-8633012f" xlink:type="simple" xsi:type="instance:XMLLink"/>
                    <hints3:property hints3:name="glass/anchorPoint" xsi:type="hints3:Property">
                        <hints3:value hints3:data="10633,10150" hints3:type="org.eclipse.swt.graphics.Point" xsi:type="hints3:PropertyValue"/>
                    </hints3:property>
                    <hints3:property hints3:name="glass/anchorPoint-StuckInfo" xsi:type="hints3:Property">
                        <hints3:value hints3:data="{EDGE,{0.7585185,1.0}}" hints3:type="{[Ljava.lang.Object;,2,enum:edu.uci.isr.bna4.logics.coordinating.MaintainStickyPointLogic$StickyMode,{[F,2,java.lang.Float,java.lang.Float}}" xsi:type="hints3:PropertyValue"/>
                    </hints3:property>
                    <hints3:property hints3:name="background/color" xsi:type="hints3:Property">
                        <hints3:value hints3:data="255,255,255" hints3:type="org.eclipse.swt.graphics.RGB" xsi:type="hints3:PropertyValue"/>
                    </hints3:property>
                </hints3:hintedElement>
                <hints3:hintedElement xsi:type="hints3:HintedElement">
                    <hints3:target xlink:href="#interfacefffffffc-40fbeb12-4f3d7217-86330153" xlink:type="simple" xsi:type="instance:XMLLink"/>
                    <hints3:property hints3:name="glass/anchorPoint" xsi:type="hints3:Property">
                        <hints3:value hints3:data="10587,10400" hints3:type="org.eclipse.swt.graphics.Point" xsi:type="hints3:PropertyValue"/>
                    </hints3:property>
                    <hints3:property hints3:name="glass/anchorPoint-StuckInfo" xsi:type="hints3:Property">
                        <hints3:value hints3:data="{EDGE,{0.75846153,0.0}}" hints3:type="{[Ljava.lang.Object;,2,enum:edu.uci.isr.bna4.logics.coordinating.MaintainStickyPointLogic$StickyMode,{[F,2,java.lang.Float,java.lang.Float}}" xsi:type="hints3:PropertyValue"/>
                    </hints3:property>
                    <hints3:property hints3:name="background/color" xsi:type="hints3:Property">
                        <hints3:value hints3:data="255,255,255" hints3:type="org.eclipse.swt.graphics.RGB" xsi:type="hints3:PropertyValue"/>
                    </hints3:property>
                </hints3:hintedElement>
                <hints3:hintedElement xsi:type="hints3:HintedElement">
                    <hints3:target xlink:href="#linkfffffffc-40fd2e61-71bb67c8-cebe0030" xlink:type="simple" xsi:type="instance:XMLLink"/>
                    <hints3:property hints3:name="glass/midpoints" xsi:type="hints3:Property">
                        <hints3:value hints3:data="{}" hints3:type="{[Lorg.eclipse.swt.graphics.Point;,0}" xsi:type="hints3:PropertyValue"/>
                    </hints3:property>
                    <hints3:property hints3:name="glass/endpoint1" xsi:type="hints3:Property">
                        <hints3:value hints3:data="10169,10155" hints3:type="org.eclipse.swt.graphics.Point" xsi:type="hints3:PropertyValue"/>
                    </hints3:property>
                    <hints3:property hints3:name="glass/endpoint2" xsi:type="hints3:Property">
                        <hints3:value hints3:data="10242,10395" hints3:type="org.eclipse.swt.graphics.Point" xsi:type="hints3:PropertyValue"/>
                    </hints3:property>
                    <hints3:property hints3:name="glass/endpoint1-StuckInfo" xsi:type="hints3:Property">
                        <hints3:value hints3:data="{EDGE_FROM_CENTER}" hints3:type="{[Ljava.lang.Object;,1,enum:edu.uci.isr.bna4.logics.coordinating.MaintainStickyPointLogic$StickyMode}" xsi:type="hints3:PropertyValue"/>
                    </hints3:property>
                    <hints3:property hints3:name="glass/endpoint2-StuckInfo" xsi:type="hints3:Property">
                        <hints3:value hints3:data="{EDGE_FROM_CENTER}" hints3:type="{[Ljava.lang.Object;,1,enum:edu.uci.isr.bna4.logics.coordinating.MaintainStickyPointLogic$StickyMode}" xsi:type="hints3:PropertyValue"/>
                    </hints3:property>
                </hints3:hintedElement>
                <hints3:hintedElement xsi:type="hints3:HintedElement">
                    <hints3:target xlink:href="#linkfffffffc-40fd7571-7c301f45-cebe005f" xlink:type="simple" xsi:type="instance:XMLLink"/>
                    <hints3:property hints3:name="glass/midpoints" xsi:type="hints3:Property">
                        <hints3:value hints3:data="{}" hints3:type="{[Lorg.eclipse.swt.graphics.Point;,0}" xsi:type="hints3:PropertyValue"/>
                    </hints3:property>
                    <hints3:property hints3:name="glass/endpoint1" xsi:type="hints3:Property">
                        <hints3:value hints3:data="10632,10155" hints3:type="org.eclipse.swt.graphics.Point" xsi:type="hints3:PropertyValue"/>
                    </hints3:property>
                    <hints3:property hints3:name="glass/endpoint2" xsi:type="hints3:Property">
                        <hints3:value hints3:data="10588,10395" hints3:type="org.eclipse.swt.graphics.Point" xsi:type="hints3:PropertyValue"/>
                    </hints3:property>
                    <hints3:property hints3:name="glass/endpoint1-StuckInfo" xsi:type="hints3:Property">
                        <hints3:value hints3:data="{EDGE_FROM_CENTER}" hints3:type="{[Ljava.lang.Object;,1,enum:edu.uci.isr.bna4.logics.coordinating.MaintainStickyPointLogic$StickyMode}" xsi:type="hints3:PropertyValue"/>
                    </hints3:property>
                    <hints3:property hints3:name="glass/endpoint2-StuckInfo" xsi:type="hints3:Property">
                        <hints3:value hints3:data="{EDGE_FROM_CENTER}" hints3:type="{[Ljava.lang.Object;,1,enum:edu.uci.isr.bna4.logics.coordinating.MaintainStickyPointLogic$StickyMode}" xsi:type="hints3:PropertyValue"/>
                    </hints3:property>
                </hints3:hintedElement>
                <hints3:hintedElement xsi:type="hints3:HintedElement">
                    <hints3:target xlink:href="#componentfffffffc-41792677-b03beb03-cebe0262" xlink:type="simple" xsi:type="instance:XMLLink"/>
                    <hints3:property hints3:name="glass/boundingBox" xsi:type="hints3:Property">
                        <hints3:value hints3:data="9975,10775,900,173" hints3:type="org.eclipse.swt.graphics.Rectangle" xsi:type="hints3:PropertyValue"/>
                    </hints3:property>
                    <hints3:property hints3:name="background/color" xsi:type="hints3:Property">
                        <hints3:value hints3:data="197,203,255" hints3:type="org.eclipse.swt.graphics.RGB" xsi:type="hints3:PropertyValue"/>
                    </hints3:property>
                </hints3:hintedElement>
                <hints3:hintedElement xsi:type="hints3:HintedElement">
                    <hints3:target xlink:href="#interfacefffffffc-417dcf35-9b587455-cebe02be" xlink:type="simple" xsi:type="instance:XMLLink"/>
                    <hints3:property hints3:name="glass/anchorPoint" xsi:type="hints3:Property">
                        <hints3:value hints3:data="10225,10525" hints3:type="org.eclipse.swt.graphics.Point" xsi:type="hints3:PropertyValue"/>
                    </hints3:property>
                    <hints3:property hints3:name="glass/anchorPoint-StuckInfo" xsi:type="hints3:Property">
                        <hints3:value hints3:data="{EDGE,{0.22222222,1.0}}" hints3:type="{[Ljava.lang.Object;,2,enum:edu.uci.isr.bna4.logics.coordinating.MaintainStickyPointLogic$StickyMode,{[F,2,java.lang.Float,java.lang.Float}}" xsi:type="hints3:PropertyValue"/>
                    </hints3:property>
                    <hints3:property hints3:name="background/color" xsi:type="hints3:Property">
                        <hints3:value hints3:data="255,255,255" hints3:type="org.eclipse.swt.graphics.RGB" xsi:type="hints3:PropertyValue"/>
                    </hints3:property>
                </hints3:hintedElement>
                <hints3:hintedElement xsi:type="hints3:HintedElement">
                    <hints3:target xlink:href="#interfacefffffffc-417e19bf-4aeb042f-cebe02e1" xlink:type="simple" xsi:type="instance:XMLLink"/>
                    <hints3:property hints3:name="glass/anchorPoint" xsi:type="hints3:Property">
                        <hints3:value hints3:data="10225,10775" hints3:type="org.eclipse.swt.graphics.Point" xsi:type="hints3:PropertyValue"/>
                    </hints3:property>
                    <hints3:property hints3:name="glass/anchorPoint-StuckInfo" xsi:type="hints3:Property">
                        <hints3:value hints3:data="{EDGE,{0.2777778,0.0}}" hints3:type="{[Ljava.lang.Object;,2,enum:edu.uci.isr.bna4.logics.coordinating.MaintainStickyPointLogic$StickyMode,{[F,2,java.lang.Float,java.lang.Float}}" xsi:type="hints3:PropertyValue"/>
                    </hints3:property>
                    <hints3:property hints3:name="background/color" xsi:type="hints3:Property">
                        <hints3:value hints3:data="255,255,255" hints3:type="org.eclipse.swt.graphics.RGB" xsi:type="hints3:PropertyValue"/>
                    </hints3:property>
                </hints3:hintedElement>
                <hints3:hintedElement xsi:type="hints3:HintedElement">
                    <hints3:target xlink:href="#interfacefffffffc-417e6457-97880f1b-cebe0305" xlink:type="simple" xsi:type="instance:XMLLink"/>
                    <hints3:property hints3:name="glass/anchorPoint" xsi:type="hints3:Property">
                        <hints3:value hints3:data="10575,10775" hints3:type="org.eclipse.swt.graphics.Point" xsi:type="hints3:PropertyValue"/>
                    </hints3:property>
                    <hints3:property hints3:name="glass/anchorPoint-StuckInfo" xsi:type="hints3:Property">
                        <hints3:value hints3:data="{EDGE,{0.6666667,0.0}}" hints3:type="{[Ljava.lang.Object;,2,enum:edu.uci.isr.bna4.logics.coordinating.MaintainStickyPointLogic$StickyMode,{[F,2,java.lang.Float,java.lang.Float}}" xsi:type="hints3:PropertyValue"/>
                    </hints3:property>
                    <hints3:property hints3:name="background/color" xsi:type="hints3:Property">
                        <hints3:value hints3:data="255,255,255" hints3:type="org.eclipse.swt.graphics.RGB" xsi:type="hints3:PropertyValue"/>
                    </hints3:property>
                </hints3:hintedElement>
                <hints3:hintedElement xsi:type="hints3:HintedElement">
                    <hints3:target xlink:href="#interfacefffffffc-417e990b-1a8d697a-cebe0328" xlink:type="simple" xsi:type="instance:XMLLink"/>
                    <hints3:property hints3:name="glass/anchorPoint" xsi:type="hints3:Property">
                        <hints3:value hints3:data="10550,10525" hints3:type="org.eclipse.swt.graphics.Point" xsi:type="hints3:PropertyValue"/>
                    </hints3:property>
                    <hints3:property hints3:name="glass/anchorPoint-StuckInfo" xsi:type="hints3:Property">
                        <hints3:value hints3:data="{EDGE,{0.7037037,1.0}}" hints3:type="{[Ljava.lang.Object;,2,enum:edu.uci.isr.bna4.logics.coordinating.MaintainStickyPointLogic$StickyMode,{[F,2,java.lang.Float,java.lang.Float}}" xsi:type="hints3:PropertyValue"/>
                    </hints3:property>
                    <hints3:property hints3:name="background/color" xsi:type="hints3:Property">
                        <hints3:value hints3:data="255,255,255" hints3:type="org.eclipse.swt.graphics.RGB" xsi:type="hints3:PropertyValue"/>
                    </hints3:property>
                </hints3:hintedElement>
                <hints3:hintedElement xsi:type="hints3:HintedElement">
                    <hints3:target xlink:href="#linkfffffffc-4180cad5-e82c2104-ea3a0056" xlink:type="simple" xsi:type="instance:XMLLink"/>
                    <hints3:property hints3:name="glass/midpoints" xsi:type="hints3:Property">
                        <hints3:value hints3:data="{}" hints3:type="{[Lorg.eclipse.swt.graphics.Point;,0}" xsi:type="hints3:PropertyValue"/>
                    </hints3:property>
                    <hints3:property hints3:name="glass/endpoint1" xsi:type="hints3:Property">
                        <hints3:value hints3:data="10225,10530" hints3:type="org.eclipse.swt.graphics.Point" xsi:type="hints3:PropertyValue"/>
                    </hints3:property>
                    <hints3:property hints3:name="glass/endpoint2" xsi:type="hints3:Property">
                        <hints3:value hints3:data="10225,10770" hints3:type="org.eclipse.swt.graphics.Point" xsi:type="hints3:PropertyValue"/>
                    </hints3:property>
                    <hints3:property hints3:name="glass/endpoint1-StuckInfo" xsi:type="hints3:Property">
                        <hints3:value hints3:data="{EDGE_FROM_CENTER}" hints3:type="{[Ljava.lang.Object;,1,enum:edu.uci.isr.bna4.logics.coordinating.MaintainStickyPointLogic$StickyMode}" xsi:type="hints3:PropertyValue"/>
                    </hints3:property>
                    <hints3:property hints3:name="glass/endpoint2-StuckInfo" xsi:type="hints3:Property">
                        <hints3:value hints3:data="{EDGE_FROM_CENTER}" hints3:type="{[Ljava.lang.Object;,1,enum:edu.uci.isr.bna4.logics.coordinating.MaintainStickyPointLogic$StickyMode}" xsi:type="hints3:PropertyValue"/>
                    </hints3:property>
                </hints3:hintedElement>
                <hints3:hintedElement xsi:type="hints3:HintedElement">
                    <hints3:target xlink:href="#linkfffffffc-4180faaf-3b96e8be-ea3a0066" xlink:type="simple" xsi:type="instance:XMLLink"/>
                    <hints3:property hints3:name="glass/midpoints" xsi:type="hints3:Property">
                        <hints3:value hints3:data="{}" hints3:type="{[Lorg.eclipse.swt.graphics.Point;,0}" xsi:type="hints3:PropertyValue"/>
                    </hints3:property>
                    <hints3:property hints3:name="glass/endpoint1" xsi:type="hints3:Property">
                        <hints3:value hints3:data="10551,10530" hints3:type="org.eclipse.swt.graphics.Point" xsi:type="hints3:PropertyValue"/>
                    </hints3:property>
                    <hints3:property hints3:name="glass/endpoint2" xsi:type="hints3:Property">
                        <hints3:value hints3:data="10575,10770" hints3:type="org.eclipse.swt.graphics.Point" xsi:type="hints3:PropertyValue"/>
                    </hints3:property>
                    <hints3:property hints3:name="glass/endpoint1-StuckInfo" xsi:type="hints3:Property">
                        <hints3:value hints3:data="{EDGE_FROM_CENTER}" hints3:type="{[Ljava.lang.Object;,1,enum:edu.uci.isr.bna4.logics.coordinating.MaintainStickyPointLogic$StickyMode}" xsi:type="hints3:PropertyValue"/>
                    </hints3:property>
                    <hints3:property hints3:name="glass/endpoint2-StuckInfo" xsi:type="hints3:Property">
                        <hints3:value hints3:data="{EDGE_FROM_CENTER}" hints3:type="{[Ljava.lang.Object;,1,enum:edu.uci.isr.bna4.logics.coordinating.MaintainStickyPointLogic$StickyMode}" xsi:type="hints3:PropertyValue"/>
                    </hints3:property>
                </hints3:hintedElement>
                
                
                
                
                
                
                
                
                
                
                
                
                
                
                
                
                
                
                
                
                
                
                
                
                
                
                
                
                
                
                
            </hints3:hintedElement>
        </hints3:hintedElement>
    </hints3:renderingHints3>
    <changes:archChange changes:id="archChangeff97002a-09d4932d-4fd8b0c2-f7a90004" xsi:type="changes:ArchChange">
        <changes:description xsi:type="instance:Description">Architecture Change Model</changes:description>
        <changes:changes changes:id="changesff97002a-09d49a45-a96f3d0d-f7a90007" changes:status="mapped" xsi:type="changes:Changes">
            <changes:description xsi:type="instance:Description">2017-11-29 16:10</changes:description>
            <changes:componentChange changes:id="componentChangeff97002a-09d49a4b-c1816f63-f7a9000a" changes:type="add" xsi:type="changes:ComponentChange">
                <changes:description xsi:type="instance:Description">New Component</changes:description>
                <changes:component xlink:href="#componentff97002a-09d49a42-09ad963d-f7a90006" xlink:type="simple" xsi:type="instance:XMLLink"/>
            </changes:componentChange>
        </changes:changes>
        <changes:changes changes:id="changesff97002a-09d69953-422461ed-f7a90046" changes:status="mapped" xsi:type="changes:Changes">
            <changes:description xsi:type="instance:Description">2017-11-29 16:12</changes:description>
            <changes:componentChange changes:id="componentChangeff97002a-09d69955-859e1787-f7a90047" changes:type="remove" xsi:type="changes:ComponentChange">
                <changes:description xsi:type="instance:Description">Remove Component</changes:description>
                <changes:component xlink:href="#Copy of componentff97002a-09d49a42-09ad963d-f7a90006" xlink:type="simple" xsi:type="instance:XMLLink"/>
                <changes:copyOfRemovedComponent types:id="Copy of componentff97002a-09d49a42-09ad963d-f7a90006" xsi:type="types:Component">
                    <types:description xsi:type="instance:Description">bootstrap</types:description>
                </changes:copyOfRemovedComponent>
            </changes:componentChange>
            <changes:componentChange changes:id="componentChangeff97002a-09d69ee0-a50d9d3e-f7a90049" changes:type="add" xsi:type="changes:ComponentChange">
                <changes:description xsi:type="instance:Description">New Component</changes:description>
                <changes:component xlink:href="#componentff97002a-09d69ee0-a10a8f1b-f7a90048" xlink:type="simple" xsi:type="instance:XMLLink"/>
            </changes:componentChange>
        </changes:changes>
        <changes:changes changes:id="changesff97002a-09d84b3a-64630606-f7a900a1" changes:status="mapped" xsi:type="changes:Changes">
            <changes:description xsi:type="instance:Description">2017-11-29 16:14</changes:description>
            <changes:componentChange changes:id="componentChangeff97002a-09d84b3b-352597b0-f7a900a2" changes:type="remove" xsi:type="changes:ComponentChange">
                <changes:description xsi:type="instance:Description">Remove Component</changes:description>
                <changes:component xlink:href="#Copy of componentff97002a-09d69ee0-a10a8f1b-f7a90048" xlink:type="simple" xsi:type="instance:XMLLink"/>
                <changes:copyOfRemovedComponent types:id="Copy of componentff97002a-09d69ee0-a10a8f1b-f7a90048" xsi:type="types:Component">
                    <types:description xsi:type="instance:Description">bootstrap</types:description>
                </changes:copyOfRemovedComponent>
            </changes:componentChange>
            <changes:componentChange changes:id="componentChangeff97002a-09d8520f-9c857bd0-f7a900a4" changes:type="add" xsi:type="changes:ComponentChange">
                <changes:description xsi:type="instance:Description">New Component</changes:description>
                <changes:component xlink:href="#componentff97002a-09d8520f-6e554146-f7a900a3" xlink:type="simple" xsi:type="instance:XMLLink"/>
            </changes:componentChange>
        </changes:changes>
        <changes:changes changes:id="changesfffffffc-40c8addf-40b7bdcd-86330029" changes:status="mapped" xsi:type="changes:Changes">
            <changes:description xsi:type="instance:Description">2017-12-10 08:16</changes:description>
            <changes:componentChange changes:id="componentChangefffffffc-40c8ade9-627914f2-86330032" changes:type="add" xsi:type="changes:ComponentChange">
                <changes:description xsi:type="instance:Description">New Component</changes:description>
                <changes:component xlink:href="#componentfffffffc-40c8adcf-462f118c-86330028" xlink:type="simple" xsi:type="instance:XMLLink"/>
            </changes:componentChange>
        </changes:changes>
        <changes:changes changes:id="changesfffffffc-40f4820d-b63420c6-86330069" changes:status="mapped" xsi:type="changes:Changes">
            <changes:description xsi:type="instance:Description">2017-12-10 09:04</changes:description>
            <changes:componentChange changes:id="componentChangefffffffc-40f4820d-eee378ad-8633006c" changes:type="add" xsi:type="changes:ComponentChange">
                <changes:description xsi:type="instance:Description">New Component</changes:description>
                <changes:component xlink:href="#componentfffffffc-40f4820d-7bd2f699-86330068" xlink:type="simple" xsi:type="instance:XMLLink"/>
            </changes:componentChange>
            <changes:componentChange changes:id="componentChangefffffffc-40fb019b-c3a63700-863300e9" changes:type="update" xsi:type="changes:ComponentChange">
                <changes:description xsi:type="instance:Description">New interface</changes:description>
                <changes:component xlink:href="#componentfffffffc-40c8adcf-462f118c-86330028" xlink:type="simple" xsi:type="instance:XMLLink"/>
                <changes:interfaceChange changes:id="interfaceChangefffffffc-40fb019b-f2b607b3-863300ea" changes:type="add" xsi:type="changes:InterfaceChange">
                    <changes:interface xlink:href="#interfacefffffffc-40fb019b-ac120043-863300e8" xlink:type="simple" xsi:type="instance:XMLLink"/>
                </changes:interfaceChange>
            </changes:componentChange>
            <changes:componentChange changes:id="componentChangefffffffc-40fb3293-9f65115e-8633010b" changes:type="update" xsi:type="changes:ComponentChange">
                <changes:description xsi:type="instance:Description">New interface</changes:description>
                <changes:component xlink:href="#componentfffffffc-40f4820d-7bd2f699-86330068" xlink:type="simple" xsi:type="instance:XMLLink"/>
                <changes:interfaceChange changes:id="interfaceChangefffffffc-40fb3293-b266b3c7-8633010f" changes:type="add" xsi:type="changes:InterfaceChange">
                    <changes:interface xlink:href="#interfacefffffffc-40fb3293-16fa1f03-8633010a" xlink:type="simple" xsi:type="instance:XMLLink"/>
                </changes:interfaceChange>
            </changes:componentChange>
            <changes:componentChange changes:id="componentChangefffffffc-40fb9d63-70424dd7-86330130" changes:type="update" xsi:type="changes:ComponentChange">
                <changes:description xsi:type="instance:Description">New interface</changes:description>
                <changes:component xlink:href="#componentfffffffc-40c8adcf-462f118c-86330028" xlink:type="simple" xsi:type="instance:XMLLink"/>
                <changes:interfaceChange changes:id="interfaceChangefffffffc-40fb9d63-def88fb0-86330132" changes:type="add" xsi:type="changes:InterfaceChange">
                    <changes:interface xlink:href="#interfacefffffffc-40fb9d63-6c2936a1-8633012f" xlink:type="simple" xsi:type="instance:XMLLink"/>
                </changes:interfaceChange>
            </changes:componentChange>
            <changes:componentChange changes:id="componentChangefffffffc-40fbeb12-8b7c7c6b-86330154" changes:type="update" xsi:type="changes:ComponentChange">
                <changes:description xsi:type="instance:Description">New interface</changes:description>
                <changes:component xlink:href="#componentfffffffc-40f4820d-7bd2f699-86330068" xlink:type="simple" xsi:type="instance:XMLLink"/>
                <changes:interfaceChange changes:id="interfaceChangefffffffc-40fbeb12-7f7b24b9-86330156" changes:type="add" xsi:type="changes:InterfaceChange">
                    <changes:interface xlink:href="#interfacefffffffc-40fbeb12-4f3d7217-86330153" xlink:type="simple" xsi:type="instance:XMLLink"/>
                </changes:interfaceChange>
            </changes:componentChange>
            <changes:linkChange changes:id="linkChangefffffffc-40fd2e69-bbb58344-cebe0031" changes:type="add" xsi:type="changes:LinkChange">
                <changes:description xsi:type="instance:Description">New Link</changes:description>
                <changes:link xlink:href="#linkfffffffc-40fd2e61-71bb67c8-cebe0030" xlink:type="simple" xsi:type="instance:XMLLink"/>
            </changes:linkChange>
            <changes:linkChange changes:id="linkChangefffffffc-40fd7571-87e709b7-cebe0060" changes:type="add" xsi:type="changes:LinkChange">
                <changes:description xsi:type="instance:Description">New Link</changes:description>
                <changes:link xlink:href="#linkfffffffc-40fd7571-7c301f45-cebe005f" xlink:type="simple" xsi:type="instance:XMLLink"/>
            </changes:linkChange>
            
            
            
            
            
            
        </changes:changes>
        <changes:changes changes:id="changesfffffffc-41792677-027ff9c7-cebe0263" changes:status="mapped" xsi:type="changes:Changes">
            <changes:description xsi:type="instance:Description">2017-12-10 11:29</changes:description>
            <changes:componentChange changes:id="componentChangefffffffc-41792687-09a085dc-cebe026c" changes:type="add" xsi:type="changes:ComponentChange">
                <changes:description xsi:type="instance:Description">New Component</changes:description>
                <changes:component xlink:href="#componentfffffffc-41792677-b03beb03-cebe0262" xlink:type="simple" xsi:type="instance:XMLLink"/>
            </changes:componentChange>
            <changes:componentChange changes:id="componentChangefffffffc-417dcf35-fa334e3c-cebe02bf" changes:type="update" xsi:type="changes:ComponentChange">
                <changes:description xsi:type="instance:Description">New interface</changes:description>
                <changes:component xlink:href="#componentfffffffc-40f4820d-7bd2f699-86330068" xlink:type="simple" xsi:type="instance:XMLLink"/>
                <changes:interfaceChange changes:id="interfaceChangefffffffc-417dcf35-df68bcdc-cebe02c0" changes:type="add" xsi:type="changes:InterfaceChange">
                    <changes:interface xlink:href="#interfacefffffffc-417dcf35-9b587455-cebe02be" xlink:type="simple" xsi:type="instance:XMLLink"/>
                </changes:interfaceChange>
            </changes:componentChange>
            <changes:componentChange changes:id="componentChangefffffffc-417e19bf-0c618075-cebe02e2" changes:type="update" xsi:type="changes:ComponentChange">
                <changes:description xsi:type="instance:Description">New interface</changes:description>
                <changes:component xlink:href="#componentfffffffc-41792677-b03beb03-cebe0262" xlink:type="simple" xsi:type="instance:XMLLink"/>
                <changes:interfaceChange changes:id="interfaceChangefffffffc-417e19bf-5b8bb289-cebe02e5" changes:type="add" xsi:type="changes:InterfaceChange">
                    <changes:interface xlink:href="#interfacefffffffc-417e19bf-4aeb042f-cebe02e1" xlink:type="simple" xsi:type="instance:XMLLink"/>
                </changes:interfaceChange>
            </changes:componentChange>
            <changes:componentChange changes:id="componentChangefffffffc-417e6457-6dab6b96-cebe0306" changes:type="update" xsi:type="changes:ComponentChange">
                <changes:description xsi:type="instance:Description">New interface</changes:description>
                <changes:component xlink:href="#componentfffffffc-41792677-b03beb03-cebe0262" xlink:type="simple" xsi:type="instance:XMLLink"/>
                <changes:interfaceChange changes:id="interfaceChangefffffffc-417e6457-8c92011a-cebe0308" changes:type="add" xsi:type="changes:InterfaceChange">
                    <changes:interface xlink:href="#interfacefffffffc-417e6457-97880f1b-cebe0305" xlink:type="simple" xsi:type="instance:XMLLink"/>
                </changes:interfaceChange>
            </changes:componentChange>
            <changes:componentChange changes:id="componentChangefffffffc-417e990b-453c80e7-cebe0329" changes:type="update" xsi:type="changes:ComponentChange">
                <changes:description xsi:type="instance:Description">New interface</changes:description>
                <changes:component xlink:href="#componentfffffffc-40f4820d-7bd2f699-86330068" xlink:type="simple" xsi:type="instance:XMLLink"/>
                <changes:interfaceChange changes:id="interfaceChangefffffffc-417e990b-085e60a0-cebe032a" changes:type="add" xsi:type="changes:InterfaceChange">
                    <changes:interface xlink:href="#interfacefffffffc-417e990b-1a8d697a-cebe0328" xlink:type="simple" xsi:type="instance:XMLLink"/>
                </changes:interfaceChange>
            </changes:componentChange>
            <changes:linkChange changes:id="linkChangefffffffc-4180cad9-9fd7d47a-ea3a0057" changes:type="add" xsi:type="changes:LinkChange">
                <changes:description xsi:type="instance:Description">New Link</changes:description>
                <changes:link xlink:href="#linkfffffffc-4180cad5-e82c2104-ea3a0056" xlink:type="simple" xsi:type="instance:XMLLink"/>
            </changes:linkChange>
            <changes:linkChange changes:id="linkChangefffffffc-4180faaf-528ab892-ea3a0067" changes:type="add" xsi:type="changes:LinkChange">
                <changes:description xsi:type="instance:Description">New Link</changes:description>
                <changes:link xlink:href="#linkfffffffc-4180faaf-3b96e8be-ea3a0066" xlink:type="simple" xsi:type="instance:XMLLink"/>
            </changes:linkChange>
            
            
            
            
            
            
        </changes:changes>
        
        
        
        
        
        
        
        
        
        
    </changes:archChange>
<types:archTypes xsi:type="types:ArchTypes">
        <types:connectorType types:id="connectorTypefffffffc-40f4d537-04793e35-8633008e" xsi:type="implementation:VariantConnectorTypeImpl">
            <types:description xsi:type="instance:Description">EventPump Type</types:description>
            <types:signature types:id="signaturefffffffc-40f4d547-2a9bf645-8633008f" xsi:type="implementation:SignatureImpl">
                <types:description xsi:type="instance:Description">in</types:description>
                <types:direction xsi:type="instance:Direction">in</types:direction>
                <implementation:implementation xsi:type="lookupimplementation:LookupImplementation">
                    <lookupimplementation:name xsi:type="lookupimplementation:LookupName">in</lookupimplementation:name>
                </implementation:implementation>
            </types:signature>
            <types:signature types:id="signaturefffffffc-40f4d547-fd08cff5-86330090" xsi:type="implementation:SignatureImpl">
                <types:description xsi:type="instance:Description">out</types:description>
                <types:direction xsi:type="instance:Direction">out</types:direction>
                <implementation:implementation xsi:type="lookupimplementation:LookupImplementation">
                    <lookupimplementation:name xsi:type="lookupimplementation:LookupName">out</lookupimplementation:name>
                </implementation:implementation>
            </types:signature>
            <implementation:implementation xsi:type="javaimplementation:JavaImplementation">
                <javaimplementation:mainClass xsi:type="javaimplementation:JavaClassFile">
                    <javaimplementation:javaClassName xsi:type="javaimplementation:JavaClassName">edu.uci.isr.myx.conn.EventPumpConnector</javaimplementation:javaClassName>
                </javaimplementation:mainClass>
            </implementation:implementation>
        </types:connectorType>
        <types:connectorType types:id="connectorTypefffffffc-40f4d547-795cbf38-86330091" xsi:type="implementation:VariantConnectorTypeImpl">
            <types:description xsi:type="instance:Description">Synchronous Type</types:description>
            <types:signature types:id="signaturefffffffc-40f4d547-e5a5df6e-86330092" xsi:type="implementation:SignatureImpl">
                <types:description xsi:type="instance:Description">in</types:description>
                <types:direction xsi:type="instance:Direction">in</types:direction>
                <implementation:implementation xsi:type="lookupimplementation:LookupImplementation">
                    <lookupimplementation:name xsi:type="lookupimplementation:LookupName">in</lookupimplementation:name>
                </implementation:implementation>
            </types:signature>
            <types:signature types:id="signaturefffffffc-40f4d547-eb7beeaa-86330093" xsi:type="implementation:SignatureImpl">
                <types:description xsi:type="instance:Description">out</types:description>
                <types:direction xsi:type="instance:Direction">out</types:direction>
                <implementation:implementation xsi:type="lookupimplementation:LookupImplementation">
                    <lookupimplementation:name xsi:type="lookupimplementation:LookupName">out</lookupimplementation:name>
                </implementation:implementation>
            </types:signature>
            <implementation:implementation xsi:type="javaimplementation:JavaImplementation">
                <javaimplementation:mainClass xsi:type="javaimplementation:JavaClassFile">
                    <javaimplementation:javaClassName xsi:type="javaimplementation:JavaClassName">edu.uci.isr.myx.conn.SynchronousProxyConnector</javaimplementation:javaClassName>
                </javaimplementation:mainClass>
            </implementation:implementation>
        </types:connectorType>
        <types:connectorType types:id="connectorTypefffffffc-40f4d547-ddab4437-86330094" xsi:type="implementation:VariantConnectorTypeImpl">
            <types:description xsi:type="instance:Description">EventPump Type - Sync &amp; Async</types:description>
            <types:signature types:id="signaturefffffffc-40f4d547-7515fefa-86330095" xsi:type="implementation:SignatureImpl">
                <types:description xsi:type="instance:Description">in</types:description>
                <types:direction xsi:type="instance:Direction">in</types:direction>
                <implementation:implementation xsi:type="lookupimplementation:LookupImplementation">
                    <lookupimplementation:name xsi:type="lookupimplementation:LookupName">in</lookupimplementation:name>
                </implementation:implementation>
            </types:signature>
            <types:signature types:id="signaturefffffffc-40f4d547-e3d04c68-86330096" xsi:type="implementation:SignatureImpl">
                <types:description xsi:type="instance:Description">out</types:description>
                <types:direction xsi:type="instance:Direction">out</types:direction>
                <implementation:implementation xsi:type="lookupimplementation:LookupImplementation">
                    <lookupimplementation:name xsi:type="lookupimplementation:LookupName">asynch</lookupimplementation:name>
                </implementation:implementation>
            </types:signature>
            <types:signature types:id="signaturefffffffc-40f4d547-7c0f05d7-86330097" xsi:type="implementation:SignatureImpl">
                <types:description xsi:type="instance:Description">out</types:description>
                <types:direction xsi:type="instance:Direction">out</types:direction>
                <implementation:implementation xsi:type="lookupimplementation:LookupImplementation">
                    <lookupimplementation:name xsi:type="lookupimplementation:LookupName">synch</lookupimplementation:name>
                </implementation:implementation>
            </types:signature>
            <implementation:implementation xsi:type="javaimplementation:JavaImplementation">
                <javaimplementation:mainClass xsi:type="javaimplementation:JavaClassFile">
                    <javaimplementation:javaClassName xsi:type="javaimplementation:JavaClassName">edu.uci.isr.myx.conn.SynchAsynchPumpConnector</javaimplementation:javaClassName>
                </javaimplementation:mainClass>
            </implementation:implementation>
        </types:connectorType>
        <types:interfaceType types:id="interfaceTypefffffffc-40f4e5d0-7d5b65f9-86330098" xsi:type="implementation:InterfaceTypeImpl">
            <types:description xsi:type="instance:Description">server service</types:description>
            <implementation:implementation xsi:type="javaimplementation:JavaImplementation">
                <javaimplementation:mainClass xsi:type="javaimplementation:JavaClassFile">
                    <javaimplementation:javaClassName xsi:type="javaimplementation:JavaClassName">tomcat.Iserver_service</javaimplementation:javaClassName>
                </javaimplementation:mainClass>
            </implementation:implementation>
        </types:interfaceType>
        <types:interfaceType types:id="interfaceTypefffffffc-40f550f9-9c233e65-8633009a" xsi:type="implementation:InterfaceTypeImpl">
            <types:description xsi:type="instance:Description">service server</types:description>
            <implementation:implementation xsi:type="javaimplementation:JavaImplementation">
                <javaimplementation:mainClass xsi:type="javaimplementation:JavaClassFile">
                    <javaimplementation:javaClassName xsi:type="javaimplementation:JavaClassName">tomcat.Iservice_server</javaimplementation:javaClassName>
                </javaimplementation:mainClass>
            </implementation:implementation>
        </types:interfaceType>
        <types:interfaceType types:id="interfaceTypefffffffc-4179dcd1-22c497de-cebe02a2" xsi:type="implementation:InterfaceTypeImpl">
            <types:description xsi:type="instance:Description">service engine</types:description>
            <implementation:implementation xsi:type="javaimplementation:JavaImplementation">
                <javaimplementation:mainClass xsi:type="javaimplementation:JavaClassFile">
                    <javaimplementation:javaClassName xsi:type="javaimplementation:JavaClassName">tomcat.Iservice_engine</javaimplementation:javaClassName>
                </javaimplementation:mainClass>
            </implementation:implementation>
        </types:interfaceType>
        <types:interfaceType types:id="interfaceTypefffffffc-417a12cc-c94b7ed8-cebe02a3" xsi:type="implementation:InterfaceTypeImpl">
            <types:description xsi:type="instance:Description">engine service</types:description>
            <implementation:implementation xsi:type="javaimplementation:JavaImplementation">
                <javaimplementation:mainClass xsi:type="javaimplementation:JavaClassFile">
                    <javaimplementation:javaClassName xsi:type="javaimplementation:JavaClassName">tomcat.Iengine_service</javaimplementation:javaClassName>
                </javaimplementation:mainClass>
            </implementation:implementation>
        </types:interfaceType>
        
        
        
        
        
    </types:archTypes>
</instance:xArch>
